molecule_benchmarks/__init__.py
molecule_benchmarks/benchmarker.py
molecule_benchmarks/dataset.py
molecule_benchmarks/model.py
molecule_benchmarks/moses_metrics.py
molecule_benchmarks/rdkit_metrics.py
molecule_benchmarks/utils.py
molecule_benchmarks/resources/mcf.csv
molecule_benchmarks/resources/wehi_pains.csv
molecule_benchmarks-0.1.14.dist-info/METADATA
molecule_benchmarks-0.1.14.dist-info/WHEEL
molecule_benchmarks-0.1.14.dist-info/entry_points.txt
molecule_benchmarks-0.1.14.dist-info/licenses/LICENSE
molecule_benchmarks-0.1.14.dist-info/RECORD
