Metadata-Version: 2.4
Name: molecule-benchmarks
Version: 0.1.14
Summary: A comprehensive benchmark suite for evaluating generative models for molecules
Project-URL: Repository, https://github.com/peteole/molecule_benchmarks
Project-URL: Issues, https://github.com/peteole/molecule_benchmarks/issues
Project-URL: Documentation, https://molecule-benchmarks.readthedocs.io/
Author-email: Ole Petersen <peteole2707@gmail.com>
License: MIT
License-File: LICENSE
Keywords: benchmarking,cheminformatics,drug-discovery,generative-models,molecules
Classifier: Development Status :: 4 - Beta
Classifier: Intended Audience :: Science/Research
Classifier: License :: OSI Approved :: MIT License
Classifier: Programming Language :: Python :: 3
Classifier: Programming Language :: Python :: 3.11
Classifier: Topic :: Scientific/Engineering :: Artificial Intelligence
Classifier: Topic :: Scientific/Engineering :: Chemistry
Requires-Python: >=3.11
Requires-Dist: fcd>=1.2.2
Requires-Dist: pandas>=2.3.0
Requires-Dist: psutil>=7.0.0
Requires-Dist: rdkit-stubs>=0.8
Requires-Dist: rdkit>=2025.3.3
Requires-Dist: requests>=2.32.4
Requires-Dist: scipy>=1.16.0
Requires-Dist: torchmetrics>=1.0.0
Requires-Dist: tqdm>=4.67.1
